fastcvapp/__init__.py
fastcvapp/examples/creativecommonsmedia/30 fps counter.webm
fastcvapp/examples/creativecommonsmedia/Elephants Dream charstart2.webm
fastcvapp/examples/creativecommonsmedia/Elephants Dream charstart2FULL_265.mp4
fastcvapp/examples/creativecommonsmedia/pose_landmarker_full.task
fastcvapp/examples/creativecommonsmedia/pose_landmarker_lite.task
fastcvapp/examples/example_backgroundsubtraction.py
fastcvapp/examples/example_cannyedge.py
fastcvapp/examples/example_haarcascade.py
fastcvapp/examples/example_identityfunc.py
fastcvapp/examples/example_mediapipe.py
fastcvapp/examples/example_nofiletest.py
fastcvapp/examples/example_rgb2rgba.py
fastcvapp/examples/example_sepiafilter.py
fastcvapp/examples/MAC_Backsub.spec
fastcvapp/examples/MAC_CannyEdge.spec
fastcvapp/examples/MAC_HaarCascade.spec
fastcvapp/examples/MAC_Mediapipe.spec
fastcvapp/examples/MAC_NofileTest.spec
fastcvapp/examples/MAC_Sepiafilter.spec
fastcvapp/examples/Readme.txt
fastcvapp/examples/WIN_Backsub.spec
fastcvapp/examples/WIN_CannyEdge.spec
fastcvapp/examples/WIN_HaarCascade.spec
fastcvapp/examples/WIN_Mediapipe.spec
fastcvapp/examples/WIN_NofileTest.spec
fastcvapp/examples/WIN_SepiaFilter.spec
fastcvapp/fastcvapp.py
fastcvapp/fcvautils.py
fastcvapp/fonts/materialdesignicons-webfont.ttf
fastcvapp/logviewer/logs.txt
fastcvapp/logviewer/matplot_timeline.py
LICENSE
fastcvapp-0.2.1.dist-info/LICENSE
fastcvapp-0.2.1.dist-info/METADATA
fastcvapp-0.2.1.dist-info/WHEEL
fastcvapp-0.2.1.dist-info/RECORD
